main.py
nolimits-0.1.0.dist-info/METADATA
nolimits-0.1.0.dist-info/WHEEL
nolimits-0.1.0.dist-info/top_level.txt
nolimits-0.1.0.dist-info/RECORD
