Metadata-Version: 2.4
Name: nolimits
Version: 0.1.0
Summary: Arbitrary precision decimal library with string-backed storage
Author: Callum
License: MIT
